MANIFEST.in
README.rst
setup.py
cirruscluster/__init__.py
cirruscluster/core.py
cirruscluster/workstation.py
cirruscluster/workstation_cli.py
cirruscluster.egg-info/PKG-INFO
cirruscluster.egg-info/SOURCES.txt
cirruscluster.egg-info/dependency_links.txt
cirruscluster.egg-info/entry_points.txt
cirruscluster.egg-info/requires.txt
cirruscluster.egg-info/top_level.txt
cirruscluster/ami/__init__.py
cirruscluster/ami/ami_cli.py
cirruscluster/ami/builder.py
cirruscluster/cluster/__init__.py
cirruscluster/cluster/cluster_cli.py
cirruscluster/cluster/config.py
cirruscluster/cluster/ec2cluster.py
cirruscluster/cluster/mapr.py
cirruscluster/ext/__init__.py
cirruscluster/ext/ansible/__init__.py
cirruscluster/ext/ansible/callbacks.py
cirruscluster/ext/ansible/color.py
cirruscluster/ext/ansible/constants.py
cirruscluster/ext/ansible/errors.py
cirruscluster/ext/ansible/module_common.py
cirruscluster/ext/ansible/callback_plugins/__init__.py
cirruscluster/ext/ansible/callback_plugins/noop.py
cirruscluster/ext/ansible/inventory/__init__.py
cirruscluster/ext/ansible/inventory/expand_hosts.py
cirruscluster/ext/ansible/inventory/group.py
cirruscluster/ext/ansible/inventory/host.py
cirruscluster/ext/ansible/inventory/ini.py
cirruscluster/ext/ansible/inventory/script.py
cirruscluster/ext/ansible/inventory/vars_plugins/__init__.py
cirruscluster/ext/ansible/inventory/vars_plugins/group_vars.py
cirruscluster/ext/ansible/playbook/__init__.py
cirruscluster/ext/ansible/playbook/play.py
cirruscluster/ext/ansible/playbook/task.py
cirruscluster/ext/ansible/runner/__init__.py
cirruscluster/ext/ansible/runner/connection.py
cirruscluster/ext/ansible/runner/poller.py
cirruscluster/ext/ansible/runner/return_data.py
cirruscluster/ext/ansible/runner/action_plugins/__init__.py
cirruscluster/ext/ansible/runner/action_plugins/add_host.py
cirruscluster/ext/ansible/runner/action_plugins/async.py
cirruscluster/ext/ansible/runner/action_plugins/copy.py
cirruscluster/ext/ansible/runner/action_plugins/debug.py
cirruscluster/ext/ansible/runner/action_plugins/fail.py
cirruscluster/ext/ansible/runner/action_plugins/fetch.py
cirruscluster/ext/ansible/runner/action_plugins/group_by.py
