Metadata-Version: 1.0
Name: cirruscluster
Version: 0.0.1-17
Summary: A batteries-included MapReduce cluster-in-a-can for scientists, researchers, and engineers.
Home-page: https://github.com/heathkh/cirruscluster
Author: Kyle Heath
Author-email: cirruscluster@gmail.com
License: MIT
Keywords: hadoop MapR mapreduce cluster cloud
Platform: UNKNOWN
